src/gutenbergPasswordGenerator/__init__.py
src/gutenbergPasswordGenerator/_version.py
src/gutenbergPasswordGenerator/gutenbergPasswordGenerator.py
gutenbergPasswordGenerator-0.3.0.dist-info/LICENSE
gutenbergPasswordGenerator-0.3.0.dist-info/METADATA
gutenbergPasswordGenerator-0.3.0.dist-info/WHEEL
gutenbergPasswordGenerator-0.3.0.dist-info/top_level.txt
gutenbergPasswordGenerator-0.3.0.dist-info/RECORD
