Metadata-Version: 2.1
Name: gutenbergPasswordGenerator
Version: 0.3.0
Summary: Python library to generate passwords using the text of classic novels
Home-page: UNKNOWN
Author: Matthew Ivancic
Author-email: matthew.ivancic91@gmail.com
License: UNKNOWN
Platform: UNKNOWN
Classifier: Programming Language :: Python :: 3
Classifier: License :: OSI Approved :: MIT License
Classifier: Operating System :: OS Independent
Requires-Python: >=3.6
License-File: LICENSE
Requires-Dist: gutenbergpy (==0.3.4)
Requires-Dist: pre-commit (==2.21.0)
Requires-Dist: pytest-cov (==4.0.0)
